odoo/addons/pos_product_display_default_code/README.rst
odoo/addons/pos_product_display_default_code/__init__.py
odoo/addons/pos_product_display_default_code/__manifest__.py
odoo/addons/pos_product_display_default_code/i18n/pos_product_display_default_code.pot
odoo/addons/pos_product_display_default_code/readme/DESCRIPTION.rst
odoo/addons/pos_product_display_default_code/readme/ROADMAP.rst
odoo/addons/pos_product_display_default_code/static/description/icon.png
odoo/addons/pos_product_display_default_code/static/description/index.html
odoo/addons/pos_product_display_default_code/static/src/js/models.js
odoo/addons/pos_product_display_default_code/templates/assets.xml
odoo14_addon_pos_product_display_default_code-14.0.1.0.1.dist-info/METADATA
odoo14_addon_pos_product_display_default_code-14.0.1.0.1.dist-info/WHEEL
odoo14_addon_pos_product_display_default_code-14.0.1.0.1.dist-info/top_level.txt
odoo14_addon_pos_product_display_default_code-14.0.1.0.1.dist-info/RECORD
