Metadata-Version: 2.1
Name: odoo14-addon-pos-product-display-default-code
Version: 14.0.1.0.1
Summary: pos: display product default code before product name
Home-page: https://github.com/OCA/pos
Author: Odoo Community Association (OCA), Akretion
Author-email: support@odoo-community.org
License: AGPL-3
Platform: UNKNOWN
Classifier: Programming Language :: Python
Classifier: Framework :: Odoo
Classifier: Framework :: Odoo :: 14.0
Classifier: License :: OSI Approved :: GNU Affero General Public License v3
Requires-Python: >=3.6
Requires-Dist: odoo (<14.1dev,>=14.0a)
